pytracy.cpython-311-x86_64-linux-gnu.so
pytracy-0.0.2.dist-info/LICENSE.txt
pytracy-0.0.2.dist-info/THIRD_PARTY_LICENSES.txt
pytracy-0.0.2.dist-info/RECORD
pytracy-0.0.2.dist-info/METADATA
pytracy-0.0.2.dist-info/WHEEL
pytracy-0.0.2.dist-info/top_level.txt
pytracy/py.typed
pytracy/__init__.pyi
