Metadata-Version: 2.1
Name: pytracy
Version: 0.0.2
Summary: python package for tracing the performance of python code
Author-email: Jakub Berkop <jakub.berkop@gmail.com>
Classifier: Programming Language :: Python :: 3
Classifier: License :: OSI Approved :: MIT License
Classifier: Operating System :: OS Independent
Requires-Python: >=3.11.0
License-File: LICENSE.txt
License-File: extra/THIRD_PARTY_LICENSES.txt
